faceid_core/__init__.py
faceid_core/deploy_configuration.py
faceid_core/face_recognition.py
faceid_core-0.1.1.dist-info/METADATA
faceid_core-0.1.1.dist-info/WHEEL
faceid_core-0.1.1.dist-info/top_level.txt
faceid_core-0.1.1.dist-info/RECORD
