Metadata-Version: 2.1
Name: faceid-core
Version: 0.1.1
Summary: Face Recognition
Home-page: https://github.com/Or1onn/faceid-core
Download-URL: https://pypi.org/project/faceid-core/
Author: Orhan Salahetdinov
Author-email: salahetdinovorxan@gmail.com
License: MIT
Keywords: FaceId,Face Recognition,Python 3
Requires-Dist: opencv-python
Requires-Dist: insightface
Requires-Dist: numpy
Requires-Dist: pathlib
Requires-Dist: sklearn
Requires-Dist: pyyaml
